{
	"info": {
		"_postman_id": "bbe76854-a044-4a7d-b3de-df8dbc00a78e",
		"name": "Super-Admin API",
		"description": "# 🚀 Get started here\n\nThis template guides you through CRUD operations (GET, POST, PUT, DELETE), variables, and tests.\n\n## 🔖 **How to use this template**\n\n#### **Step 1: Send requests**\n\nRESTful APIs allow you to perform CRUD operations using the POST, GET, PUT, and DELETE HTTP methods.\n\nThis collection contains each of these [request](https://learning.postman.com/docs/sending-requests/requests/) types. Open each request and click \"Send\" to see what happens.\n\n#### **Step 2: View responses**\n\nObserve the response tab for status code (200 OK), response time, and size.\n\n#### **Step 3: Send new Body data**\n\nUpdate or add new data in \"Body\" in the POST request. Typically, Body data is also used in PUT request.\n\n```\n{\n    \"name\": \"Add your name in the body\"\n}\n\n ```\n\n#### **Step 4: Update the variable**\n\nVariables enable you to store and reuse values in Postman. We have created a [variable](https://learning.postman.com/docs/sending-requests/variables/) called `base_url` with the sample request [https://postman-api-learner.glitch.me](https://postman-api-learner.glitch.me). Replace it with your API endpoint to customize this collection.\n\n#### **Step 5: Add tests in the \"Scripts\" tab**\n\nAdding tests to your requests can help you confirm that your API is working as expected. You can write test scripts in JavaScript and view the output in the \"Test Results\" tab.\n\n<img src=\"https://content.pstmn.io/fa30ea0a-373d-4545-a668-e7b283cca343/aW1hZ2UucG5n\" width=\"2162\" height=\"1530\">\n\n## 💪 Pro tips\n\n- Use folders to group related requests and organize the collection.\n    \n- Add more [scripts](https://learning.postman.com/docs/writing-scripts/intro-to-scripts/) to verify if the API works as expected and execute workflows.\n    \n\n## 💡Related templates\n\n[API testing basics](https://go.postman.co/redirect/workspace?type=personal&collectionTemplateId=e9a37a28-055b-49cd-8c7e-97494a21eb54&sourceTemplateId=ddb19591-3097-41cf-82af-c84273e56719)  \n[API documentation](https://go.postman.co/redirect/workspace?type=personal&collectionTemplateId=e9c28f47-1253-44af-a2f3-20dce4da1f18&sourceTemplateId=ddb19591-3097-41cf-82af-c84273e56719)  \n[Authorization methods](https://go.postman.co/redirect/workspace?type=personal&collectionTemplateId=31a9a6ed-4cdf-4ced-984c-d12c9aec1c27&sourceTemplateId=ddb19591-3097-41cf-82af-c84273e56719)",
		"schema": "https://schema.getpostman.com/json/collection/v2.1.0/collection.json",
		"_exporter_id": "46298657",
		"_collection_link": "https://raza-5882330.postman.co/workspace/37dfb414-d0c5-4cca-8838-c68e8ad8649c/collection/46298657-bbe76854-a044-4a7d-b3de-df8dbc00a78e?action=share&source=collection_link&creator=46298657"
	},
	"item": [
		{
			"name": "Auth",
			"item": [
				{
					"name": "login",
					"event": [
						{
							"listen": "test",
							"script": {
								"exec": [
									"const res = pm.response.json();\r",
									"\r",
									"if (res.token) {\r",
									"  pm.environment.set(\"token\", res.token);\r",
									"}\r",
									""
								],
								"type": "text/javascript",
								"packages": {}
							}
						}
					],
					"request": {
						"auth": {
							"type": "bearer",
							"bearer": [
								{
									"key": "token",
									"value": "{{token}}",
									"type": "string"
								}
							]
						},
						"method": "POST",
						"header": [],
						"body": {
							"mode": "raw",
							"raw": "{ \"email\": \"superadmin@example.com\", \"password\": \"Test1234!\" }",
							"options": {
								"raw": {
									"language": "json"
								}
							}
						},
						"url": {
							"raw": "{{base_url}}api/v1/auth/login",
							"host": [
								"{{base_url}}api"
							],
							"path": [
								"v1",
								"auth",
								"login"
							]
						}
					},
					"response": []
				}
			]
		},
		{
			"name": "Users",
			"item": [
				{
					"name": "Get all users",
					"request": {
						"auth": {
							"type": "bearer",
							"bearer": [
								{
									"key": "token",
									"value": "{{token}}",
									"type": "string"
								}
							]
						},
						"method": "GET",
						"header": [],
						"url": {
							"raw": "{{base_url}}api/v1/superadmin/users",
							"host": [
								"{{base_url}}api"
							],
							"path": [
								"v1",
								"superadmin",
								"users"
							]
						}
					},
					"response": []
				},
				{
					"name": "List all users (filters, pagination)",
					"request": {
						"auth": {
							"type": "bearer",
							"bearer": [
								{
									"key": "token",
									"value": "{{token}}",
									"type": "string"
								}
							]
						},
						"method": "GET",
						"header": [],
						"url": {
							"raw": "{{base_url}}api/v1/superadmin/users?page=1&limit=10&search=user",
							"host": [
								"{{base_url}}api"
							],
							"path": [
								"v1",
								"superadmin",
								"users"
							],
							"query": [
								{
									"key": "page",
									"value": "1"
								},
								{
									"key": "limit",
									"value": "10"
								},
								{
									"key": "search",
									"value": "user"
								}
							]
						}
					},
					"response": []
				},
				{
					"name": "Get user detail by id",
					"protocolProfileBehavior": {
						"disableBodyPruning": true
					},
					"request": {
						"auth": {
							"type": "bearer",
							"bearer": [
								{
									"key": "token",
									"value": "{{token}}",
									"type": "string"
								}
							]
						},
						"method": "GET",
						"header": [],
						"body": {
							"mode": "raw",
							"raw": "{ \"email\": \"superadmin@example.com\", \"password\": \"Test1234!\" }"
						},
						"url": {
							"raw": "{{base_url}}api/v1/superadmin/users/{{userId}}",
							"host": [
								"{{base_url}}api"
							],
							"path": [
								"v1",
								"superadmin",
								"users",
								"{{userId}}"
							]
						}
					},
					"response": []
				},
				{
					"name": "Create  new user",
					"request": {
						"auth": {
							"type": "bearer",
							"bearer": [
								{
									"key": "token",
									"value": "{{token}}",
									"type": "string"
								}
							]
						},
						"method": "POST",
						"header": [],
						"body": {
							"mode": "raw",
							"raw": "{\"name\": \"test-user\", \"email\": \"testuser12@gmail.com\", \"password\": \"Test1234!\"}",
							"options": {
								"raw": {
									"language": "json"
								}
							}
						},
						"url": {
							"raw": "{{base_url}}api/v1/superadmin/users",
							"host": [
								"{{base_url}}api"
							],
							"path": [
								"v1",
								"superadmin",
								"users"
							]
						}
					},
					"response": []
				},
				{
					"name": "Update User",
					"request": {
						"auth": {
							"type": "bearer",
							"bearer": [
								{
									"key": "token",
									"value": "{{token}}",
									"type": "string"
								}
							]
						},
						"method": "PUT",
						"header": [],
						"body": {
							"mode": "raw",
							"raw": "{\"name\": \"user-1\", \"email\": \"another123@test.com\", \"password\": \"Test4321!\"}",
							"options": {
								"raw": {
									"language": "json"
								}
							}
						},
						"url": {
							"raw": "{{base_url}}api/v1/superadmin/users/{{userId}}",
							"host": [
								"{{base_url}}api"
							],
							"path": [
								"v1",
								"superadmin",
								"users",
								"{{userId}}"
							]
						}
					},
					"response": []
				},
				{
					"name": "Delete User",
					"request": {
						"auth": {
							"type": "bearer",
							"bearer": [
								{
									"key": "token",
									"value": "{{token}}",
									"type": "string"
								}
							]
						},
						"method": "DELETE",
						"header": [],
						"body": {
							"mode": "raw",
							"raw": "{ \"email\": \"superadmin@example.com\", \"password\": \"Test1234!\" }"
						},
						"url": {
							"raw": "{{base_url}}api/v1/superadmin/users/{{userId}}",
							"host": [
								"{{base_url}}api"
							],
							"path": [
								"v1",
								"superadmin",
								"users",
								"{{userId}}"
							]
						}
					},
					"response": []
				}
			]
		},
		{
			"name": "Roles",
			"item": [
				{
					"name": "Get all roles",
					"request": {
						"auth": {
							"type": "bearer",
							"bearer": [
								{
									"key": "token",
									"value": "{{token}}",
									"type": "string"
								}
							]
						},
						"method": "GET",
						"header": [],
						"url": {
							"raw": "{{baseurl}}api/v1/superadmin/roles/",
							"host": [
								"{{baseurl}}api"
							],
							"path": [
								"v1",
								"superadmin",
								"roles",
								""
							]
						}
					},
					"response": []
				},
				{
					"name": "Create new role",
					"request": {
						"auth": {
							"type": "bearer",
							"bearer": [
								{
									"key": "token",
									"value": "{{token}}",
									"type": "string"
								}
							]
						},
						"method": "POST",
						"header": [],
						"body": {
							"mode": "raw",
							"raw": "{\"name\": \"viewer\", \"permissions\": [\"read:audit-logs\",\"read:analytics\"]}",
							"options": {
								"raw": {
									"language": "json"
								}
							}
						},
						"url": {
							"raw": "{{baseurl}}api/v1/superadmin/roles/",
							"host": [
								"{{baseurl}}api"
							],
							"path": [
								"v1",
								"superadmin",
								"roles",
								""
							]
						}
					},
					"response": []
				},
				{
					"name": "Update roles",
					"request": {
						"auth": {
							"type": "bearer",
							"bearer": [
								{
									"key": "token",
									"value": "{{token}}",
									"type": "string"
								}
							]
						},
						"method": "PUT",
						"header": [],
						"body": {
							"mode": "raw",
							"raw": "{\"permissions\": [\"read:roles\",\r\n          \"create:roles\",\"read:users\",\r\n          \"create:users\",\r\n          \"update:users\",\r\n          \"delete:users\"]}",
							"options": {
								"raw": {
									"language": "json"
								}
							}
						},
						"url": {
							"raw": "{{baseurl}}api/v1/superadmin/roles/{{roleId}}",
							"host": [
								"{{baseurl}}api"
							],
							"path": [
								"v1",
								"superadmin",
								"roles",
								"{{roleId}}"
							]
						}
					},
					"response": []
				},
				{
					"name": "assign-roles",
					"request": {
						"auth": {
							"type": "bearer",
							"bearer": [
								{
									"key": "token",
									"value": "{{token}}",
									"type": "string"
								}
							]
						},
						"method": "POST",
						"header": [],
						"body": {
							"mode": "raw",
							"raw": "{\"userId\": \"68b466c277e22d1772a15abb\", \"roleId\": \"68b3312c832b921aa6b012e2\"}",
							"options": {
								"raw": {
									"language": "json"
								}
							}
						},
						"url": {
							"raw": "{{base_url}}api/v1/superadmin/assign-role",
							"host": [
								"{{base_url}}api"
							],
							"path": [
								"v1",
								"superadmin",
								"assign-role"
							]
						}
					},
					"response": []
				}
			]
		},
		{
			"name": "Audit-logs",
			"item": [
				{
					"name": "audit-logs basic",
					"request": {
						"auth": {
							"type": "bearer",
							"bearer": [
								{
									"key": "token",
									"value": "{{token}}",
									"type": "string"
								}
							]
						},
						"method": "GET",
						"header": [],
						"url": {
							"raw": "{{base_url}}api/v1/superadmin/audit-logs",
							"host": [
								"{{base_url}}api"
							],
							"path": [
								"v1",
								"superadmin",
								"audit-logs"
							]
						}
					},
					"response": []
				},
				{
					"name": "Filter by User",
					"request": {
						"auth": {
							"type": "bearer",
							"bearer": [
								{
									"key": "token",
									"value": "{{token}}",
									"type": "string"
								}
							]
						},
						"method": "GET",
						"header": [],
						"url": {
							"raw": "{{base_url}}api/v1/superadmin/audit-logs?user={{userId}}",
							"host": [
								"{{base_url}}api"
							],
							"path": [
								"v1",
								"superadmin",
								"audit-logs"
							],
							"query": [
								{
									"key": "user",
									"value": "{{userId}}"
								}
							]
						}
					},
					"response": []
				},
				{
					"name": "Filter by Action",
					"request": {
						"auth": {
							"type": "bearer",
							"bearer": [
								{
									"key": "token",
									"value": "{{token}}",
									"type": "string"
								}
							]
						},
						"method": "GET",
						"header": [],
						"url": {
							"raw": "{{base_url}}api/v1/superadmin/audit-logs?action=CREATE_USER",
							"host": [
								"{{base_url}}api"
							],
							"path": [
								"v1",
								"superadmin",
								"audit-logs"
							],
							"query": [
								{
									"key": "action",
									"value": "CREATE_USER"
								}
							]
						}
					},
					"response": []
				},
				{
					"name": "Filter by Date Range",
					"request": {
						"auth": {
							"type": "bearer",
							"bearer": [
								{
									"key": "token",
									"value": "{{token}}",
									"type": "string"
								}
							]
						},
						"method": "GET",
						"header": [],
						"url": {
							"raw": "{{base_url}}api/v1/superadmin/audit-logs?startDate=2025-08-01&endDate=2025-08-30",
							"host": [
								"{{base_url}}api"
							],
							"path": [
								"v1",
								"superadmin",
								"audit-logs"
							],
							"query": [
								{
									"key": "startDate",
									"value": "2025-08-01"
								},
								{
									"key": "endDate",
									"value": "2025-08-30"
								}
							]
						}
					},
					"response": []
				},
				{
					"name": "Pagination",
					"request": {
						"auth": {
							"type": "bearer",
							"bearer": [
								{
									"key": "token",
									"value": "{{token}}",
									"type": "string"
								}
							]
						},
						"method": "GET",
						"header": [],
						"url": {
							"raw": "{{base_url}}api/v1/superadmin/audit-logs?page=4&limit=5",
							"host": [
								"{{base_url}}api"
							],
							"path": [
								"v1",
								"superadmin",
								"audit-logs"
							],
							"query": [
								{
									"key": "page",
									"value": "4"
								},
								{
									"key": "limit",
									"value": "5"
								}
							]
						}
					},
					"response": []
				}
			]
		},
		{
			"name": "Analytics",
			"item": [
				{
					"name": "summary",
					"request": {
						"auth": {
							"type": "bearer",
							"bearer": [
								{
									"key": "token",
									"value": "{{token}}",
									"type": "string"
								}
							]
						},
						"method": "GET",
						"header": [],
						"url": {
							"raw": "{{base_url}}api/v1/superadmin/analytics/summary",
							"host": [
								"{{base_url}}api"
							],
							"path": [
								"v1",
								"superadmin",
								"analytics",
								"summary"
							]
						}
					},
					"response": []
				}
			]
		}
	],
	"event": [
		{
			"listen": "prerequest",
			"script": {
				"type": "text/javascript",
				"exec": [
					""
				]
			}
		},
		{
			"listen": "test",
			"script": {
				"type": "text/javascript",
				"exec": [
					""
				]
			}
		}
	],
	"variable": [
		{
			"key": "id",
			"value": "1"
		},
		{
			"key": "base_url",
			"value": "https://postman-rest-api-learner.glitch.me/"
		},
		{
			"key": "token",
			"value": "",
			"type": "default"
		},
		{
			"key": "userId",
			"value": "",
			"type": "default"
		},
		{
			"key": "roleId",
			"value": "",
			"type": "default"
		}
	]
}